augmenting/__init__.py
augmenting-0.0.0.dist-info/METADATA
augmenting-0.0.0.dist-info/WHEEL
augmenting-0.0.0.dist-info/top_level.txt
augmenting-0.0.0.dist-info/RECORD
